tiai/__init__.py
tiai/app_recognition.py
tiai/image_viewer.py
tiai/ui_infrared_recognition.py
tiai/ui_infrared_recognition.ui
tiai/__pycache__/__init__.cpython-39.pyc
tiai/__pycache__/app_recognition.cpython-39.pyc
tiai/__pycache__/image_viewer.cpython-39.pyc
tiai/__pycache__/ui_infrared_recognition.cpython-39.pyc
tiai/mediapip/__init__.py
tiai/mediapip/face.py
tiai/mediapip/face_mesh.py
tiai/mediapip/hand.py
tiai/mediapip/pose.py
tiai/mediapip/selfie.py
tiai/mediapip/__pycache__/__init__.cpython-39.pyc
tiai/mediapip/__pycache__/face.cpython-39.pyc
tiai/mediapip/__pycache__/face_mesh.cpython-39.pyc
tiai/mediapip/__pycache__/hand.cpython-39.pyc
tiai/mediapip/__pycache__/pose.cpython-39.pyc
tiai/mediapip/__pycache__/selfie.cpython-39.pyc
IRT_AI-0.0.1a0.dist-info/LICENSE
IRT_AI-0.0.1a0.dist-info/METADATA
IRT_AI-0.0.1a0.dist-info/WHEEL
IRT_AI-0.0.1a0.dist-info/entry_points.txt
IRT_AI-0.0.1a0.dist-info/top_level.txt
IRT_AI-0.0.1a0.dist-info/RECORD
